<?xml version="1.0" encoding="windows-1252" ?>
<!DOCTYPE ViewObject SYSTEM "jbo_03_01.dtd">
<!---->
<ViewObject
  xmlns="http://xmlns.oracle.com/bc4j"
  Name="LincuUserInfoVO"
  Version="12.2.1.11.57"
  InheritPersonalization="merge"
  SelectListFlags="1"
  FromListFlags="1"
  WhereFlags="1"
  BindingStyle="OracleName"
  CustomQuery="false"
  SelectAllAttributes="false"
  PageIterMode="Full"
  RowClass="com.linCu.model.view.LincuUserInfoVORowImpl"
  ComponentClass="com.linCu.model.view.LincuUserInfoVOImpl"
  ComponentInterface="com.linCu.model.view.common.LincuUserInfoVO"
  ClientProxyName="com.linCu.model.view.client.LincuUserInfoVOClient">
  <DesignTime>
    <Attr Name="_codeGenFlag2" Value="Access|Coll|VarAccess"/>
    <Attr Name="_isCodegen" Value="true"/>
  </DesignTime>
  <Variable
    Name="bindCreditUnionId"
    Kind="viewcriteria"
    Type="java.lang.String"/>
  <Variable
    Name="bindCreatedBy"
    Kind="viewcriteria"
    Type="java.lang.String"/>
  <ViewAccessor
    Name="GenderVA"
    ViewObjectName="com.linCu.model.vvo.GenderVVO"
    RowLevelBinds="true"/>
  <ViewAccessor
    Name="LinCuRolesVA"
    ViewObjectName="com.linCu.model.vvo.LinCuRolesVVO"
    RowLevelBinds="true">
    <ViewCriteriaUsage
      Name="QueryByLincu"
      FullName="com.linCu.model.vvo.LinCuRolesVVO.QueryByLincu"/>
  </ViewAccessor>
  <ViewAccessor
    Name="LincuUnionsVA"
    ViewObjectName="com.linCu.model.vvo.LincuUnionsVVO"
    RowLevelBinds="true">
    <ViewCriteriaUsage
      Name="QueryByCreditUnion"
      FullName="com.linCu.model.vvo.LincuUnionsVVO.QueryByCreditUnion"/>
    <ParameterMap>
      <PIMap Variable="bindCreditUnionId">
        <TransientExpression
          Name="ExpressionScript"><![CDATA[adf.context.current.sessionScope.get('creditUnionId')]]></TransientExpression>
      </PIMap>
    </ParameterMap>
  </ViewAccessor>
  <ViewAccessor
    Name="LincuBranchesVA"
    ViewObjectName="com.linCu.model.vvo.LincuBranchesVVO"
    RowLevelBinds="true">
    <ViewCriteriaUsage
      Name="QueryByCreditUnion"
      FullName="com.linCu.model.vvo.LincuBranchesVVO.QueryByCreditUnion"/>
    <ParameterMap>
      <PIMap Variable="bindCreditUnionId">
        <TransientExpression
          Name="ExpressionScript"><![CDATA[CreditUnionId]]></TransientExpression>
      </PIMap>
    </ParameterMap>
  </ViewAccessor>
  <ViewAccessor
    Name="LookUpDataVA"
    ViewObjectName="com.linCu.model.vvo.LookUpDataVVO"
    RowLevelBinds="true">
    <ViewCriteriaUsage
      Name="QueryByLookupType"
      FullName="com.linCu.model.vvo.LookUpDataVVO.QueryByLookupType"/>
    <ParameterMap>
      <PIMap Variable="bindLookUpType">
        <TransientExpression
          Name="ExpressionScript"><![CDATA['USER_TYPE_CODE']]></TransientExpression>
      </PIMap>
    </ParameterMap>
  </ViewAccessor>
  <ViewAccessor
    Name="SecurityQuestionsVA"
    ViewObjectName="com.linCu.model.vvo.LookUpDataVVO"
    RowLevelBinds="true">
    <ViewCriteriaUsage
      Name="QueryByLookupType"
      FullName="com.linCu.model.vvo.LookUpDataVVO.QueryByLookupType"/>
    <ParameterMap>
      <PIMap Variable="bindLookUpType">
        <TransientExpression
          trustMode="untrusted"
          Name="ExpressionScript"><![CDATA['SECURITY_QUESTION']]></TransientExpression>
      </PIMap>
    </ParameterMap>
  </ViewAccessor>
  <ViewAccessor
    Name="CreditUnionLinCuRolesVA"
    ViewObjectName="com.linCu.model.vvo.LinCuRolesVVO"
    RowLevelBinds="true">
    <ViewCriteriaUsage
      Name="QueryCreditUnionRoles"
      FullName="com.linCu.model.vvo.LinCuRolesVVO.QueryCreditUnionRoles"/>
  </ViewAccessor>
  <ViewAccessor
    Name="FCBRolesVA"
    ViewObjectName="com.linCu.model.vvo.LinCuRolesVVO"
    RowLevelBinds="true">
    <ViewCriteriaUsage
      Name="QueryByFCB"
      FullName="com.linCu.model.vvo.LinCuRolesVVO.QueryByFCB"/>
  </ViewAccessor>
  <ListBinding
    Name="LOV_Gender"
    ListVOName="GenderVA"
    ListRangeSize="-1"
    NullValueFlag="none"
    MRUCount="0">
    <AttrArray Name="AttrNames">
      <Item Value="Gender"/>
    </AttrArray>
    <AttrArray Name="AttrExpressions"/>
    <AttrArray Name="ListAttrNames">
      <Item Value="GenderCode"/>
    </AttrArray>
    <AttrArray Name="ListDisplayAttrNames">
      <Item Value="GenderName"/>
    </AttrArray>
    <DisplayCriteria/>
  </ListBinding>
  <ListBinding
    Name="LOV_UserRole"
    ListVOName="LinCuRolesVA"
    ListRangeSize="-1"
    NullValueFlag="none"
    MRUCount="0">
    <AttrArray Name="AttrNames">
      <Item Value="UserRole"/>
    </AttrArray>
    <AttrArray Name="AttrExpressions"/>
    <AttrArray Name="ListAttrNames">
      <Item Value="Role"/>
    </AttrArray>
    <AttrArray Name="ListDisplayAttrNames">
      <Item Value="RoleDescription"/>
    </AttrArray>
    <DisplayCriteria/>
  </ListBinding>
  <ListBinding
    Name="LOV_CreditUnionId"
    ListVOName="LincuUnionsVA"
    ListRangeSize="-1"
    NullValueFlag="start"
    MRUCount="0"
    NullValueId="${adfBundle['oracle.javatools.resourcebundle.SystemBundle']['NULL_VALUE_RESID']}">
    <AttrArray Name="AttrNames">
      <Item Value="CreditUnionId"/>
    </AttrArray>
    <AttrArray Name="AttrExpressions"/>
    <AttrArray Name="ListAttrNames">
      <Item Value="CreditUnionId"/>
    </AttrArray>
    <AttrArray Name="ListDisplayAttrNames">
      <Item Value="CreditUnionName"/>
    </AttrArray>
    <DisplayCriteria/>
  </ListBinding>
  <ListBinding
    Name="LOV_CreditUnionBranchId"
    ListVOName="LincuBranchesVA"
    ListRangeSize="-1"
    NullValueFlag="start"
    MRUCount="0"
    NullValueId="${adfBundle['oracle.javatools.resourcebundle.SystemBundle']['NULL_VALUE_RESID']}">
    <AttrArray Name="AttrNames">
      <Item Value="CreditUnionBranchId"/>
    </AttrArray>
    <AttrArray Name="AttrExpressions"/>
    <AttrArray Name="ListAttrNames">
      <Item Value="CreditUnionBranchId"/>
    </AttrArray>
    <AttrArray Name="ListDisplayAttrNames">
      <Item Value="CreditUnionBranchName"/>
    </AttrArray>
    <DisplayCriteria/>
  </ListBinding>
  <ListBinding
    Name="LOV_UserTypeCode"
    ListVOName="LookUpDataVA"
    ListRangeSize="-1"
    NullValueFlag="start"
    NullValueId="${adfBundle['oracle.javatools.resourcebundle.SystemBundle']['NULL_VALUE_RESID']}"
    MRUCount="0">
    <AttrArray Name="AttrNames">
      <Item Value="UserTypeCode"/>
    </AttrArray>
    <AttrArray Name="AttrExpressions"/>
    <AttrArray Name="ListAttrNames">
      <Item Value="LookupCode"/>
    </AttrArray>
    <AttrArray Name="ListDisplayAttrNames">
      <Item Value="LookupDesc"/>
    </AttrArray>
    <DisplayCriteria/>
  </ListBinding>
  <ListBinding
    Name="LOV_SecurityQustn"
    ListVOName="SecurityQuestionsVA"
    ListRangeSize="-1"
    NullValueFlag="start"
    NullValueId="${adfBundle['oracle.javatools.resourcebundle.SystemBundle']['NULL_VALUE_RESID']}"
    MRUCount="0">
    <AttrArray Name="AttrNames">
      <Item Value="SecurityQustn"/>
    </AttrArray>
    <AttrArray Name="AttrExpressions"/>
    <AttrArray Name="ListAttrNames">
      <Item Value="LookupCode"/>
    </AttrArray>
    <AttrArray Name="ListDisplayAttrNames">
      <Item Value="LookupDesc"/>
    </AttrArray>
    <DisplayCriteria/>
  </ListBinding>
  <ListBinding
    Name="LOV_SecurityQustn1"
    ListVOName="SecurityQuestionsVA"
    ListRangeSize="-1"
    NullValueFlag="start"
    NullValueId="${adfBundle['oracle.javatools.resourcebundle.SystemBundle']['NULL_VALUE_RESID']}"
    MRUCount="0">
    <AttrArray Name="AttrNames">
      <Item Value="SecurityQustn1"/>
    </AttrArray>
    <AttrArray Name="AttrExpressions"/>
    <AttrArray Name="ListAttrNames">
      <Item Value="LookupCode"/>
    </AttrArray>
    <AttrArray Name="ListDisplayAttrNames">
      <Item Value="LookupDesc"/>
    </AttrArray>
    <DisplayCriteria/>
  </ListBinding>
  <ListBinding
    Name="LOV_SecurityQustn2"
    ListVOName="SecurityQuestionsVA"
    ListRangeSize="-1"
    NullValueFlag="start"
    NullValueId="${adfBundle['oracle.javatools.resourcebundle.SystemBundle']['NULL_VALUE_RESID']}"
    MRUCount="0">
    <AttrArray Name="AttrNames">
      <Item Value="SecurityQustn2"/>
    </AttrArray>
    <AttrArray Name="AttrExpressions"/>
    <AttrArray Name="ListAttrNames">
      <Item Value="LookupCode"/>
    </AttrArray>
    <AttrArray Name="ListDisplayAttrNames">
      <Item Value="LookupDesc"/>
    </AttrArray>
    <DisplayCriteria/>
  </ListBinding>
  <ListBinding
    Name="LOV_SecurityQustn3"
    ListVOName="SecurityQuestionsVA"
    ListRangeSize="-1"
    NullValueFlag="start"
    NullValueId="${adfBundle['oracle.javatools.resourcebundle.SystemBundle']['NULL_VALUE_RESID']}"
    MRUCount="0">
    <AttrArray Name="AttrNames">
      <Item Value="SecurityQustn3"/>
    </AttrArray>
    <AttrArray Name="AttrExpressions"/>
    <AttrArray Name="ListAttrNames">
      <Item Value="LookupCode"/>
    </AttrArray>
    <AttrArray Name="ListDisplayAttrNames">
      <Item Value="LookupDesc"/>
    </AttrArray>
    <DisplayCriteria/>
  </ListBinding>
  <ListBinding
    Name="LOV_SecurityQustn4"
    ListVOName="SecurityQuestionsVA"
    ListRangeSize="-1"
    NullValueFlag="start"
    NullValueId="${adfBundle['oracle.javatools.resourcebundle.SystemBundle']['NULL_VALUE_RESID']}"
    MRUCount="0">
    <AttrArray Name="AttrNames">
      <Item Value="SecurityQustn4"/>
    </AttrArray>
    <AttrArray Name="AttrExpressions"/>
    <AttrArray Name="ListAttrNames">
      <Item Value="LookupCode"/>
    </AttrArray>
    <AttrArray Name="ListDisplayAttrNames">
      <Item Value="LookupDesc"/>
    </AttrArray>
    <DisplayCriteria/>
  </ListBinding>
  <ListBinding
    Name="LOV_UserRole1"
    ListVOName="CreditUnionLinCuRolesVA"
    ListRangeSize="-1"
    NullValueFlag="none"
    MRUCount="0">
    <AttrArray Name="AttrNames">
      <Item Value="UserRole"/>
    </AttrArray>
    <AttrArray Name="AttrExpressions"/>
    <AttrArray Name="ListAttrNames">
      <Item Value="Role"/>
    </AttrArray>
    <AttrArray Name="ListDisplayAttrNames">
      <Item Value="RoleDescription"/>
    </AttrArray>
    <DisplayCriteria/>
  </ListBinding>
  <ListBinding
    Name="LOV_UserRole12"
    ListVOName="FCBRolesVA"
    ListRangeSize="-1"
    NullValueFlag="none"
    MRUCount="0">
    <AttrArray Name="AttrNames">
      <Item Value="UserRole"/>
    </AttrArray>
    <AttrArray Name="AttrExpressions"/>
    <AttrArray Name="ListAttrNames">
      <Item Value="Role"/>
    </AttrArray>
    <AttrArray Name="ListDisplayAttrNames">
      <Item Value="RoleDescription"/>
    </AttrArray>
    <DisplayCriteria/>
  </ListBinding>
  <EntityUsage
    Name="LincuUserInfoEO"
    Entity="com.linCu.model.entity.LincuUserInfoEO"/>
  <ViewAttribute
    Name="UserId"
    IsNotNull="true"
    PrecisionRule="true"
    EntityAttrName="UserId"
    EntityUsage="LincuUserInfoEO"
    AliasName="USER_ID"
    IsUpdateable="while_insert"/>
  <ViewAttribute
    Name="FirstName"
    PrecisionRule="true"
    EntityAttrName="FirstName"
    EntityUsage="LincuUserInfoEO"
    AliasName="FIRST_NAME"
    IsUpdateable="while_insert">
    <Properties>
      <SchemaBasedProperties>
        <DISPLAYWIDTH
          Value="37"/>
        <LABEL
          ResId="FIRST_NAME"/>
      </SchemaBasedProperties>
    </Properties>
  </ViewAttribute>
  <ViewAttribute
    Name="LastName"
    PrecisionRule="true"
    EntityAttrName="LastName"
    EntityUsage="LincuUserInfoEO"
    AliasName="LAST_NAME"
    IsUpdateable="while_insert">
    <Properties>
      <SchemaBasedProperties>
        <DISPLAYWIDTH
          Value="37"/>
        <LABEL
          ResId="LAST_NAME"/>
      </SchemaBasedProperties>
    </Properties>
  </ViewAttribute>
  <ViewAttribute
    Name="CreditUnionId"
    IsNotNull="true"
    PrecisionRule="true"
    EntityAttrName="CreditUnionId"
    EntityUsage="LincuUserInfoEO"
    AliasName="CREDIT_UNION_ID"
    LOVName="LOV_CreditUnionId">
    <Properties>
      <SchemaBasedProperties>
        <DISPLAYWIDTH
          Value="37"/>
        <LABEL
          ResId="CREDIT_UNION"/>
        <CONTROLTYPE
          Value="choice"/>
      </SchemaBasedProperties>
    </Properties>
  </ViewAttribute>
  <ViewAttribute
    Name="CreditUnionBranchId"
    IsNotNull="true"
    PrecisionRule="true"
    EntityAttrName="CreditUnionBranchId"
    EntityUsage="LincuUserInfoEO"
    AliasName="CREDIT_UNION_BRANCH_ID"
    LOVName="LOV_CreditUnionBranchId">
    <Properties>
      <SchemaBasedProperties>
        <DISPLAYWIDTH
          Value="37"/>
        <LABEL
          ResId="BRANCH_NAME"/>
        <CONTROLTYPE
          Value="choice"/>
      </SchemaBasedProperties>
    </Properties>
  </ViewAttribute>
  <ViewAttribute
    Name="UserTypeCode"
    IsNotNull="true"
    PrecisionRule="true"
    EntityAttrName="UserTypeCode"
    EntityUsage="LincuUserInfoEO"
    AliasName="USER_TYPE_CODE"
    LOVName="LOV_UserTypeCode">
    <Properties>
      <SchemaBasedProperties>
        <CONTROLTYPE
          Value="choice"/>
        <DISPLAYWIDTH
          Value="37"/>
        <LABEL
          ResId="TYPE"/>
      </SchemaBasedProperties>
    </Properties>
  </ViewAttribute>
  <ViewAttribute
    Name="UserRole"
    IsNotNull="true"
    PrecisionRule="true"
    EntityAttrName="UserRole"
    EntityUsage="LincuUserInfoEO"
    AliasName="USER_ROLE"
    LOVName="LOV_UserRole1"
    LOVFinder="SwitchRoles">
    <Properties>
      <SchemaBasedProperties>
        <DISPLAYWIDTH
          Value="37"/>
        <LABEL
          ResId="ROLE"/>
        <CONTROLTYPE
          Value="choice"/>
      </SchemaBasedProperties>
    </Properties>
    <Dependencies>
      <Item
        Value="SwitchRoles"/>
    </Dependencies>
  </ViewAttribute>
  <ViewAttribute
    Name="UserSupervisor"
    IsNotNull="true"
    PrecisionRule="true"
    EntityAttrName="UserSupervisor"
    EntityUsage="LincuUserInfoEO"
    AliasName="USER_SUPERVISOR">
    <Properties>
      <SchemaBasedProperties>
        <DISPLAYWIDTH
          Value="37"/>
        <LABEL
          ResId="SUPERVISOR"/>
      </SchemaBasedProperties>
    </Properties>
  </ViewAttribute>
  <ViewAttribute
    Name="Email"
    IsNotNull="true"
    PrecisionRule="true"
    EntityAttrName="Email"
    EntityUsage="LincuUserInfoEO"
    AliasName="EMAIL"
    IsUpdateable="while_insert">
    <Properties>
      <SchemaBasedProperties>
        <DISPLAYWIDTH
          Value="37"/>
      </SchemaBasedProperties>
    </Properties>
  </ViewAttribute>
  <ViewAttribute
    Name="MobilePhoneNumber"
    PrecisionRule="true"
    EntityAttrName="MobilePhoneNumber"
    EntityUsage="LincuUserInfoEO"
    AliasName="MOBILE_PHONE_NUMBER">
    <Properties>
      <SchemaBasedProperties>
        <DISPLAYWIDTH
          Value="37"/>
        <LABEL
          ResId="CONTACT_NUMBER"/>
      </SchemaBasedProperties>
    </Properties>
  </ViewAttribute>
  <ViewAttribute
    Name="DateOfBirth"
    PrecisionRule="true"
    EntityAttrName="DateOfBirth"
    EntityUsage="LincuUserInfoEO"
    AliasName="DATE_OF_BIRTH">
    <Properties>
      <SchemaBasedProperties>
        <DISPLAYWIDTH
          Value="33"/>
        <LABEL
          ResId="DATE_OF_BIRTH"/>
      </SchemaBasedProperties>
    </Properties>
  </ViewAttribute>
  <ViewAttribute
    Name="Gender"
    IsNotNull="true"
    PrecisionRule="true"
    EntityAttrName="Gender"
    EntityUsage="LincuUserInfoEO"
    AliasName="GENDER"
    LOVName="LOV_Gender">
    <Properties>
      <SchemaBasedProperties>
        <DISPLAYWIDTH
          Value="37"/>
        <CONTROLTYPE
          Value="radio"/>
      </SchemaBasedProperties>
    </Properties>
  </ViewAttribute>
  <ViewAttribute
    Name="CreatedBy"
    IsNotNull="true"
    PrecisionRule="true"
    EntityAttrName="CreatedBy"
    EntityUsage="LincuUserInfoEO"
    AliasName="CREATED_BY"
    IsUpdateable="while_insert"/>
  <ViewAttribute
    Name="CreationDate"
    IsNotNull="true"
    PrecisionRule="true"
    EntityAttrName="CreationDate"
    EntityUsage="LincuUserInfoEO"
    AliasName="CREATION_DATE"
    IsUpdateable="while_insert"/>
  <ViewAttribute
    Name="LastUpdatedBy"
    IsNotNull="true"
    PrecisionRule="true"
    EntityAttrName="LastUpdatedBy"
    EntityUsage="LincuUserInfoEO"
    AliasName="LAST_UPDATED_BY"/>
  <ViewAttribute
    Name="LastUpdateDate"
    IsNotNull="true"
    PrecisionRule="true"
    EntityAttrName="LastUpdateDate"
    EntityUsage="LincuUserInfoEO"
    AliasName="LAST_UPDATE_DATE"/>
  <ViewAttribute
    Name="ObjectVersionId"
    IsNotNull="true"
    PrecisionRule="true"
    EntityAttrName="ObjectVersionId"
    EntityUsage="LincuUserInfoEO"
    AliasName="OBJECT_VERSION_ID"/>
  <ViewAttribute
    Name="LastApprovedBy"
    IsNotNull="true"
    PrecisionRule="true"
    EntityAttrName="LastApprovedBy"
    EntityUsage="LincuUserInfoEO"
    AliasName="LAST_APPROVED_BY"/>
  <ViewAttribute
    Name="LastApprovedDate"
    IsNotNull="true"
    PrecisionRule="true"
    EntityAttrName="LastApprovedDate"
    EntityUsage="LincuUserInfoEO"
    AliasName="LAST_APPROVED_DATE"/>
  <ViewAttribute
    Name="Password"
    IsNotNull="true"
    PrecisionRule="true"
    EntityAttrName="Password"
    EntityUsage="LincuUserInfoEO"
    AliasName="PASSWORD">
    <Properties>
      <SchemaBasedProperties>
        <DISPLAYWIDTH
          Value="37"/>
      </SchemaBasedProperties>
    </Properties>
  </ViewAttribute>
  <ViewAttribute
    Name="UserName"
    IsNotNull="true"
    PrecisionRule="true"
    EntityAttrName="UserName"
    EntityUsage="LincuUserInfoEO"
    AliasName="USER_NAME">
    <Properties>
      <SchemaBasedProperties>
        <DISPLAYWIDTH
          Value="37"/>
        <LABEL
          ResId="LOGIN_NAME"/>
      </SchemaBasedProperties>
    </Properties>
  </ViewAttribute>
  <ViewAttribute
    Name="SecurityQustn"
    PrecisionRule="true"
    EntityAttrName="SecurityQustn"
    EntityUsage="LincuUserInfoEO"
    AliasName="SECURITY_QUSTN"
    LOVName="LOV_SecurityQustn">
    <Properties>
      <SchemaBasedProperties>
        <CONTROLTYPE
          Value="choice"/>
        <LABEL
          ResId="SECURITY_QUESTION_1"/>
      </SchemaBasedProperties>
    </Properties>
  </ViewAttribute>
  <ViewAttribute
    Name="SecurityQustnAns"
    PrecisionRule="true"
    EntityAttrName="SecurityQustnAns"
    EntityUsage="LincuUserInfoEO"
    AliasName="SECURITY_QUSTN_ANS">
    <Properties>
      <SchemaBasedProperties>
        <LABEL
          ResId="ANSWER"/>
      </SchemaBasedProperties>
    </Properties>
  </ViewAttribute>
  <ViewAttribute
    Name="FirstLoginFlag"
    IsNotNull="true"
    PrecisionRule="true"
    EntityAttrName="FirstLoginFlag"
    EntityUsage="LincuUserInfoEO"
    AliasName="FIRST_LOGIN_FLAG"/>
  <ViewAttribute
    Name="SecurityQustn1"
    PrecisionRule="true"
    EntityAttrName="SecurityQustn1"
    EntityUsage="LincuUserInfoEO"
    AliasName="SECURITY_QUSTN1"
    LOVName="LOV_SecurityQustn1">
    <Properties>
      <SchemaBasedProperties>
        <CONTROLTYPE
          Value="choice"/>
        <LABEL
          ResId="SECURITY_QUESTION_2"/>
      </SchemaBasedProperties>
    </Properties>
  </ViewAttribute>
  <ViewAttribute
    Name="SecurityQustn2"
    PrecisionRule="true"
    EntityAttrName="SecurityQustn2"
    EntityUsage="LincuUserInfoEO"
    AliasName="SECURITY_QUSTN2"
    LOVName="LOV_SecurityQustn2">
    <Properties>
      <SchemaBasedProperties>
        <CONTROLTYPE
          Value="choice"/>
        <LABEL
          ResId="SECURITY_QUESTION_3"/>
      </SchemaBasedProperties>
    </Properties>
  </ViewAttribute>
  <ViewAttribute
    Name="SecurityQustn3"
    PrecisionRule="true"
    EntityAttrName="SecurityQustn3"
    EntityUsage="LincuUserInfoEO"
    AliasName="SECURITY_QUSTN3"
    LOVName="LOV_SecurityQustn3">
    <Properties>
      <SchemaBasedProperties>
        <CONTROLTYPE
          Value="choice"/>
        <LABEL
          ResId="SECURITY_QUESTION_4"/>
      </SchemaBasedProperties>
    </Properties>
  </ViewAttribute>
  <ViewAttribute
    Name="SecurityQustn4"
    PrecisionRule="true"
    EntityAttrName="SecurityQustn4"
    EntityUsage="LincuUserInfoEO"
    AliasName="SECURITY_QUSTN4"
    LOVName="LOV_SecurityQustn4">
    <Properties>
      <SchemaBasedProperties>
        <CONTROLTYPE
          Value="choice"/>
        <LABEL
          ResId="SECURITY_QUESTION_5"/>
      </SchemaBasedProperties>
    </Properties>
  </ViewAttribute>
  <ViewAttribute
    Name="SecurityQustnAns1"
    PrecisionRule="true"
    EntityAttrName="SecurityQustnAns1"
    EntityUsage="LincuUserInfoEO"
    AliasName="SECURITY_QUSTN_ANS1">
    <Properties>
      <SchemaBasedProperties>
        <LABEL
          ResId="ANSWER"/>
      </SchemaBasedProperties>
    </Properties>
  </ViewAttribute>
  <ViewAttribute
    Name="SecurityQustnAns2"
    PrecisionRule="true"
    EntityAttrName="SecurityQustnAns2"
    EntityUsage="LincuUserInfoEO"
    AliasName="SECURITY_QUSTN_ANS2">
    <Properties>
      <SchemaBasedProperties>
        <LABEL
          ResId="ANSWER"/>
      </SchemaBasedProperties>
    </Properties>
  </ViewAttribute>
  <ViewAttribute
    Name="SecurityQustnAns3"
    PrecisionRule="true"
    EntityAttrName="SecurityQustnAns3"
    EntityUsage="LincuUserInfoEO"
    AliasName="SECURITY_QUSTN_ANS3">
    <Properties>
      <SchemaBasedProperties>
        <LABEL
          ResId="ANSWER"/>
      </SchemaBasedProperties>
    </Properties>
  </ViewAttribute>
  <ViewAttribute
    Name="SecurityQustnAns4"
    PrecisionRule="true"
    EntityAttrName="SecurityQustnAns4"
    EntityUsage="LincuUserInfoEO"
    AliasName="SECURITY_QUSTN_ANS4">
    <Properties>
      <SchemaBasedProperties>
        <LABEL
          ResId="ANSWER"/>
      </SchemaBasedProperties>
    </Properties>
  </ViewAttribute>
  <ViewAttribute
    Name="SwitchRoles"
    IsSelected="false"
    IsPersistent="false"
    PrecisionRule="true"
    Type="java.lang.String"
    ColumnType="$none$"
    SQLType="VARCHAR"/>
  <ViewCriteria
    Name="QueryUserInfo"
    ViewObjectName="com.linCu.model.view.LincuUserInfoVO"
    Conjunction="AND">
    <Properties Name="_Props">
      <CustomProperties>
        <Property
          Name="autoExecute"
          Value="false"/>
        <Property
          Name="mode"
          Value="Basic"/>
        <Property
          Name="allowConjunctionOverride"
          Value="false"/>
        <Property
          Name="showInList"
          Value="true"/>
        <Property
          Name="displayOperators"
          Value="InAdvancedMode"/>
      </CustomProperties>
    </Properties>
    <ViewCriteriaRow
      Name="LincuUserInfoVOCriteria_row_0"
      UpperColumns="1">
      <ViewCriteriaItem
        Name="LincuUserInfoVOCriteria_LincuUserInfoVOCriteria_row_0_FirstName"
        ViewAttribute="FirstName"
        Operator="="
        Conjunction="AND"
        Required="Optional"/>
      <ViewCriteriaItem
        Name="LastName"
        ViewAttribute="LastName"
        Operator="="
        Conjunction="AND"
        Required="Optional"/>
      <ViewCriteriaItem
        Name="CreditUnionId"
        ViewAttribute="CreditUnionId"
        Operator="="
        Conjunction="AND"
        Required="Optional"/>
      <ViewCriteriaItem
        Name="LincuUserInfoVOCriteria_LincuUserInfoVOCriteria_row_0_CreditUnionBranchId"
        ViewAttribute="CreditUnionBranchId"
        Operator="="
        Conjunction="AND"
        Required="Optional"/>
      <ViewCriteriaItem
        Name="UserRole"
        ViewAttribute="UserRole"
        Operator="="
        Conjunction="AND"
        Required="Optional"/>
      <ViewCriteriaItem
        Name="Email"
        ViewAttribute="Email"
        Operator="="
        Conjunction="AND"
        Required="Optional"/>
      <ViewCriteriaItem
        Name="MobilePhoneNumber"
        ViewAttribute="MobilePhoneNumber"
        Operator="="
        Conjunction="AND"
        Required="Optional"/>
      <ViewCriteriaItem
        Name="LincuUserInfoVOCriteria_LincuUserInfoVOCriteria_row_0_DateOfBirth"
        ViewAttribute="DateOfBirth"
        Operator="="
        Conjunction="AND"
        Required="Optional"/>
      <ViewCriteriaItem
        Name="Gender"
        ViewAttribute="Gender"
        Operator="="
        Conjunction="AND"
        Required="Optional"/>
      <ViewCriteriaItem
        Name="UserName"
        ViewAttribute="UserName"
        Operator="="
        Conjunction="AND"
        Required="Optional"/>
    </ViewCriteriaRow>
  </ViewCriteria>
  <ViewCriteria
    Name="QueryByCreditUnion"
    ViewObjectName="com.linCu.model.view.LincuUserInfoVO"
    Conjunction="AND">
    <Properties Name="_Props">
      <CustomProperties>
        <Property
          Name="autoExecute"
          Value="false"/>
        <Property
          Name="mode"
          Value="Basic"/>
        <Property
          Name="allowConjunctionOverride"
          Value="true"/>
        <Property
          Name="showInList"
          Value="true"/>
        <Property
          Name="displayOperators"
          Value="InAdvancedMode"/>
      </CustomProperties>
    </Properties>
    <ViewCriteriaRow
      Name="LincuUserInfoVOCriteria_row_0"
      UpperColumns="1">
      <ViewCriteriaItem
        Name="CreditUnionId"
        ViewAttribute="CreditUnionId"
        Operator="="
        Conjunction="AND"
        Value=":bindCreditUnionId"
        IsBindVarValue="true"
        Required="Optional"/>
      <ViewCriteriaItem
        Name="QueryByCreditUnion_LincuUserInfoVOCriteria_row_0_CreatedBy"
        ViewAttribute="CreatedBy"
        Operator="="
        Conjunction="OR"
        Value=":bindCreatedBy"
        IsBindVarValue="true"
        Required="Optional"/>
    </ViewCriteriaRow>
  </ViewCriteria>
  <ClientInterface
    Name="__clientInterface">
    <Method
      Name="createUser"
      MethodName="createUser">
      <Return
        Name="_return_type_"
        Type="void"/>
      <Parameter
        Name="user"
        Type="java.lang.String"/>
    </Method>
    <Method
      Name="updateUser"
      MethodName="updateUser">
      <Return
        Name="_return_type_"
        Type="void"/>
      <Parameter
        Name="user"
        Type="java.lang.String"/>
    </Method>
    <Method
      Name="forgotPassword"
      MethodName="forgotPassword">
      <Return
        Name="_return_type_"
        Type="void"/>
    </Method>
    <Method
      Name="updatePassword"
      MethodName="updatePassword">
      <Return
        Name="_return_type_"
        Type="void"/>
      <Parameter
        Name="password"
        Type="java.lang.String"/>
    </Method>
  </ClientInterface>
  <ResourceBundle>
    <PropertiesBundle
      PropertiesFile="com.linCu.model.LinCuModelBundle"/>
  </ResourceBundle>
</ViewObject>
